ynot3/__init__.py
ynot3/buttons.py
ynot3/colors.py
ynot3/gui.py
ynot3/shapes.py
ynot3/widgets.py
ynot3-1.2.3.dist-info/METADATA
ynot3-1.2.3.dist-info/WHEEL
ynot3-1.2.3.dist-info/entry_points.txt
ynot3-1.2.3.dist-info/RECORD
