Metadata-Version: 2.1
Name: ynot3
Version: 1.2.3
Summary: An image annotator for Xorg & Wayland using pygame
Home-page: https://github.com/fdev31/ynot3
License: GPL
Author: fdev31
Author-email: fdev31@gmail.com
Requires-Python: >=3.8,<4.0
Classifier: License :: Other/Proprietary License
Classifier: Programming Language :: Python :: 3
Classifier: Programming Language :: Python :: 3.8
Classifier: Programming Language :: Python :: 3.9
Classifier: Programming Language :: Python :: 3.10
Classifier: Programming Language :: Python :: 3.11
Classifier: Programming Language :: Python :: 3.12
Requires-Dist: pygame (>=2.4.0,<3.0.0)
